acsuite/__init__.py
acsuite/_metadata.py
acsuite/py.typed
acsuite_orangechannel-6.0.0.dist-info/METADATA
acsuite_orangechannel-6.0.0.dist-info/WHEEL
acsuite_orangechannel-6.0.0.dist-info/top_level.txt
acsuite_orangechannel-6.0.0.dist-info/RECORD
