Metadata-Version: 2.1
Name: acsuite-orangechannel
Version: 6.0.0
Summary: Frame-based cutting/trimming/splicing of audio with VapourSynth and FFmpeg.
Home-page: https://github.com/OrangeChannel/acsuite
Author: Dave
Author-email: orangechannel@pm.me
License: UNLICENSE
Project-URL: Documentation, https://acsuite.readthedocs.io/en/latest/
Project-URL: Source, https://github.com/OrangeChannel/acsuite/blob/master/acsuite/__init__.py
Project-URL: Tracker, https://github.com/OrangeChannel/acsuite/issues
Keywords: audio vapoursynth encoding trim cut ffmpeg
Platform: UNKNOWN
Classifier: Intended Audience :: End Users/Desktop
Classifier: License :: Public Domain
Classifier: Natural Language :: English
Classifier: Operating System :: OS Independent
Classifier: Programming Language :: Python :: 3.8
Classifier: Topic :: Multimedia :: Sound/Audio
Classifier: Typing :: Typed
Requires-Python: >=3.8
Requires-Dist: VapourSynth
Provides-Extra: vfr_progress_bar
Requires-Dist: rich (>=6.1.2) ; extra == 'vfr_progress_bar'
